zsvg/__init__.py
zsvg/load.cpython-312-darwin.so
zsvg/proc.cpython-312-darwin.so
zsvg/sec.cpython-312-darwin.so
zsvg-0.1.0.21.dist-info/METADATA
zsvg-0.1.0.21.dist-info/WHEEL
zsvg-0.1.0.21.dist-info/top_level.txt
zsvg-0.1.0.21.dist-info/RECORD
