Metadata-Version: 2.1
Name: zsvg
Version: 0.1.0.21
Summary: A svg utilities package
Author: zm741234
Classifier: Programming Language :: Python :: 3
Classifier: License :: Other/Proprietary License
Classifier: Operating System :: OS Independent
Requires-Python: >=3.12
